Metadata-Version: 2.1
Name: odoo14-addon-project-stage-mgmt
Version: 14.0.1.0.1.dev8
Summary: Allows to assign and create stages on project creation wizard
Home-page: https://github.com/OCA/project
Author: ForgeFlow, Odoo Community Association (OCA)
Author-email: support@odoo-community.org
License: AGPL-3
Platform: UNKNOWN
Classifier: Programming Language :: Python
Classifier: Framework :: Odoo
Classifier: Framework :: Odoo :: 14.0
Classifier: License :: OSI Approved :: GNU Affero General Public License v3
Classifier: Development Status :: 4 - Beta
Requires-Python: >=3.6
Requires-Dist: odoo <14.1dev,>=14.0a
